ayrshare/__init__.py
ayrshare/ayrshare.py
social_post_api-1.2.4.dist-info/METADATA
social_post_api-1.2.4.dist-info/WHEEL
social_post_api-1.2.4.dist-info/top_level.txt
social_post_api-1.2.4.dist-info/RECORD
