Metadata-Version: 2.1
Name: social-post-api
Version: 1.2.4
Summary: Social Media API: Schedule posts, get analytics, manage comments for Instagram, X/Twitter, Facebook, YouTube, LinkedIn, Google Business Profile, Pinterest, Telegram, TikTok, and Reddit.
Home-page: https://www.ayrshare.com
Author: Ayrshare
Author-email: support@ayrshare.com
License: Apache License 2.0
Project-URL: Documentation, https://docs.ayrshare.com
Project-URL: Source, https://github.com/ayrshare/social-post-api-python
Keywords: Ayrshare,Social Media API,Social Networks,Social Media Management,Social API,Social Publishing,Social Posting,Social Analytics,Social Automation,Agency Social,Multiple User Posting,Instagram,YouTube API,X API,Twitter API,Facebook API,LinkedIn API,Reddit API,Telegram API,Pinterest API,Google Business Profile API,TikTok API
Requires-Dist: requests
